certbot_dns_hcloud/__init__.py
certbot_dns_hcloud/dns_hcloud.py
certbot_dns_hcloud-1.1.2.dist-info/licenses/LICENSE.txt
certbot_dns_hcloud-1.1.2.dist-info/METADATA
certbot_dns_hcloud-1.1.2.dist-info/WHEEL
certbot_dns_hcloud-1.1.2.dist-info/entry_points.txt
certbot_dns_hcloud-1.1.2.dist-info/top_level.txt
certbot_dns_hcloud-1.1.2.dist-info/RECORD
