Metadata-Version: 2.4
Name: certbot-dns-hcloud
Version: 1.1.2
Summary: This is a certbot plugin to perform dns-01 authentication using the Hetzner Cloud (Console) API
Home-page: https://github.com/EMX107/certbot-dns-hcloud
Author: EMX107
License: Apache License 2.0
Requires-Python: >=3.13
License-File: LICENSE.txt
Requires-Dist: hcloud>=2.11.0
Requires-Dist: certbot>=5.1.0
Requires-Dist: setuptools
Dynamic: author
Dynamic: description
Dynamic: description-content-type
Dynamic: home-page
Dynamic: license
Dynamic: license-file
Dynamic: requires-dist
Dynamic: requires-python
Dynamic: summary
